covidstates/__init__.py
covidstates/states.py
covidstatetracker-0.0.3.dist-info/METADATA
covidstatetracker-0.0.3.dist-info/WHEEL
covidstatetracker-0.0.3.dist-info/licenses/LICENSE
covidstatetracker-0.0.3.dist-info/RECORD
