Metadata-Version: 2.1
Name: covidstatetracker
Version: 0.0.3
Summary: A package to analyze COVID-19 data using the NYTimes COVID-19 dataset
Project-URL: Homepage, https://github.com/DevonSchwartz/COVIDStateTracker
Author-email: Devon Schwartz <devon.s.schwartz@gmail.com>
License: MIT License
Classifier: License :: OSI Approved :: MIT License
Classifier: Operating System :: OS Independent
Classifier: Programming Language :: Python :: 3
Requires-Python: >=3.7
